[
  {
    "name": "kotlin.reflect.jvm.internal.ReflectionFactoryImpl",
    "allDeclaredConstructors": true
  },
  {
    "name": "kotlin.KotlinVersion",
    "allPublicMethods": true,
    "allDeclaredFields": true,
    "allDeclaredMethods": true,
    "allDeclaredConstructors": true
  },
  {
    "name": "kotlin.KotlinVersion[]"
  },
  {
    "name": "kotlin.KotlinVersion$Companion"
  },
  {
    "name": "kotlin.KotlinVersion$Companion[]"
  },
  {
    "name": "kotlin.internal.jdk8.JDK8PlatformImplementations",
    "allPublicMethods": true,
    "allDeclaredFields": true,
    "allDeclaredMethods": true,
    "allDeclaredConstructors": true
  },
  {
    "name": "ch.qos.logback.classic.AsyncAppender",
    "allDeclaredConstructors": true,
    "allPublicConstructors": true,
    "allDeclaredMethods": true,
    "allPublicMethods": true,
    "allDeclaredFields": true,
    "allPublicFields": true,
    "allDeclaredClasses": true,
    "allPublicClasses": true
  },
  {
    "name": "ch.qos.logback.classic.encoder.PatternLayoutEncoder",
    "allDeclaredConstructors": true,
    "allPublicConstructors": true,
    "allDeclaredMethods": true,
    "allPublicMethods": true,
    "allDeclaredFields": true,
    "allPublicFields": true,
    "allDeclaredClasses": true,
    "allPublicClasses": true
  },
  {
    "name": "ch.qos.logback.classic.pattern.DateConverter",
    "allDeclaredConstructors": true,
    "allPublicConstructors": true,
    "allDeclaredMethods": true,
    "allPublicMethods": true,
    "allDeclaredFields": true,
    "allPublicFields": true,
    "allDeclaredClasses": true,
    "allPublicClasses": true
  },
  {
    "name": "ch.qos.logback.classic.pattern.LevelConverter",
    "allDeclaredConstructors": true,
    "allPublicConstructors": true,
    "allDeclaredMethods": true,
    "allPublicMethods": true,
    "allDeclaredFields": true,
    "allPublicFields": true,
    "allDeclaredClasses": true,
    "allPublicClasses": true
  },
  {
    "name": "ch.qos.logback.classic.pattern.LineSeparatorConverter",
    "allDeclaredConstructors": true,
    "allPublicConstructors": true,
    "allDeclaredMethods": true,
    "allPublicMethods": true,
    "allDeclaredFields": true,
    "allPublicFields": true,
    "allDeclaredClasses": true,
    "allPublicClasses": true
  },
  {
    "name": "ch.qos.logback.classic.pattern.LoggerConverter",
    "allDeclaredConstructors": true,
    "allPublicConstructors": true,
    "allDeclaredMethods": true,
    "allPublicMethods": true,
    "allDeclaredFields": true,
    "allPublicFields": true,
    "allDeclaredClasses": true,
    "allPublicClasses": true
  },
  {
    "name": "ch.qos.logback.classic.pattern.MessageConverter",
    "allDeclaredConstructors": true,
    "allPublicConstructors": true,
    "allDeclaredMethods": true,
    "allPublicMethods": true,
    "allDeclaredFields": true,
    "allPublicFields": true,
    "allDeclaredClasses": true,
    "allPublicClasses": true
  },
  {
    "name": "ch.qos.logback.classic.pattern.ThreadConverter",
    "allDeclaredConstructors": true,
    "allPublicConstructors": true,
    "allDeclaredMethods": true,
    "allPublicMethods": true,
    "allDeclaredFields": true,
    "allPublicFields": true,
    "allDeclaredClasses": true,
    "allPublicClasses": true
  },
  {
    "name": "ch.qos.logback.core.ConsoleAppender",
    "allDeclaredConstructors": true,
    "allPublicConstructors": true,
    "allDeclaredMethods": true,
    "allPublicMethods": true,
    "allDeclaredFields": true,
    "allPublicFields": true,
    "allDeclaredClasses": true,
    "allPublicClasses": true
  },
  {
    "name": "ch.qos.logback.core.FileAppender",
    "allDeclaredConstructors": true,
    "allPublicConstructors": true,
    "allDeclaredMethods": true,
    "allPublicMethods": true,
    "allDeclaredFields": true,
    "allPublicFields": true,
    "allDeclaredClasses": true,
    "allPublicClasses": true
  }
]